setup.cfg
setup.py
agileid/__init__.py
agileid.egg-info/PKG-INFO
agileid.egg-info/SOURCES.txt
agileid.egg-info/dependency_links.txt
agileid.egg-info/requires.txt
agileid.egg-info/top_level.txt