Metadata-Version: 1.1
Name: agileid
Version: 0.1.2
Summary: Generate and manage AgileID identifiers
Home-page: https://github.com/kurttheviking/agileid-py
Author: Kurt Ericson
Author-email: kurttheviking@outlook.com
License: ISC
Download-URL: https://github.com/kurttheviking/agileid-py/tarball/v0.1.2
Keywords: agileid,short objectid,encode objectid
Platform: UNKNOWN
Classifier: Development Status :: 3 - Alpha
Classifier: Intended Audience :: Developers
Classifier: License :: OSI Approved :: ISC License (ISCL)
Classifier: Programming Language :: Python :: 2
Classifier: Programming Language :: Python :: 2.7
